ceccomp/__init__.py
ceccomp/ceccomp
ceccomp-3.5.dist-info/METADATA
ceccomp-3.5.dist-info/WHEEL
ceccomp-3.5.dist-info/entry_points.txt
ceccomp-3.5.dist-info/top_level.txt
ceccomp-3.5.dist-info/RECORD
