Metadata-Version: 2.4
Name: ceccomp
Version: 3.5
Summary: A C-based seccomp analysis tool
Author-email: dbgbgtf <dudududumaxver@outlook.com>
License-Expression: GPL-3.0-or-later
